onemod/__init__.py
onemod/main.py
onemod/pipeline.py
onemod/backend/__init__.py
onemod/backend/jobmon_backend.py
onemod/backend/local_backend.py
onemod/backend/utils.py
onemod/config/__init__.py
onemod/config/base.py
onemod/constraints/__init__.py
onemod/constraints/base.py
onemod/constraints/functions.py
onemod/dtypes/__init__.py
onemod/dtypes/column_spec.py
onemod/dtypes/data.py
onemod/dtypes/filepath.py
onemod/dtypes/unique_sequence.py
onemod/fsutils/__init__.py
onemod/fsutils/config_loader.py
onemod/fsutils/data_loader.py
onemod/fsutils/interface.py
onemod/fsutils/io.py
onemod/fsutils/path_manager.py
onemod/io/__init__.py
onemod/io/base.py
onemod/serialization/__init__.py
onemod/serialization/functions.py
onemod/stage/__init__.py
onemod/stage/base.py
onemod/utils/__init__.py
onemod/utils/decorators.py
onemod/validation/__init__.py
onemod/validation/error_handling.py
onemod/validation/validators.py
onemod-1.3.1.dist-info/licenses/LICENSE
onemod-1.3.1.dist-info/METADATA
onemod-1.3.1.dist-info/WHEEL
onemod-1.3.1.dist-info/entry_points.txt
onemod-1.3.1.dist-info/top_level.txt
onemod-1.3.1.dist-info/RECORD
