Metadata-Version: 2.4
Name: onemod
Version: 1.3.1
Summary: An orchestration package for statistical modeling pipelines.
Author-email: IHME Math Sciences <ihme.math.sciences@gmail.com>
License: BSD 2-Clause License
Project-URL: github, https://github.com/ihmeuw-msca/OneMod
Classifier: License :: OSI Approved :: BSD License
Classifier: Intended Audience :: Developers
Classifier: Intended Audience :: Science/Research
Classifier: Natural Language :: English
Classifier: Programming Language :: Python :: 3.10
Classifier: Programming Language :: Python :: 3.11
Classifier: Programming Language :: Python :: 3.12
Requires-Python: <3.13,>=3.10
License-File: LICENSE
Requires-Dist: dill
Requires-Dist: fire
Requires-Dist: pandas
Requires-Dist: polars
Requires-Dist: pyarrow
Requires-Dist: pydantic
Requires-Dist: pyyaml
Requires-Dist: tomli
Requires-Dist: tomli_w
Provides-Extra: dev
Requires-Dist: build; extra == "dev"
Requires-Dist: deptry; extra == "dev"
Requires-Dist: mypy<2.0.0,>=1.12.0; extra == "dev"
Requires-Dist: pandas-stubs; extra == "dev"
Requires-Dist: pre-commit<5.0.0,>=4.0.1; extra == "dev"
Requires-Dist: pytest>=7.0.0; extra == "dev"
Requires-Dist: pytest-cov>=5.0.0; extra == "dev"
Requires-Dist: python-dotenv; extra == "dev"
Requires-Dist: ruff<1.0.0,>=0.7.0; extra == "dev"
Requires-Dist: types-PyYAML; extra == "dev"
Provides-Extra: docs
Requires-Dist: furo; extra == "docs"
Requires-Dist: sphinx; extra == "docs"
Requires-Dist: sphinx-autodoc-typehints; extra == "docs"
Provides-Extra: jobmon
Requires-Dist: jobmon_installer_ihme>=10.9.0; extra == "jobmon"
Provides-Extra: test
Requires-Dist: pytest>=7.0.0; extra == "test"
Requires-Dist: pytest-cov>=5.0.0; extra == "test"
Requires-Dist: python-dotenv; extra == "test"
Dynamic: license-file
